urpameasure/__about__.py
urpameasure/__init__.py
urpameasure/globals.py
urpameasure/management_console.py
urpameasure/py.typed
urpameasure/sydesk.py
urpameasure/urpameasure.py
urpameasure/utils.py
urpameasure-0.1.1.dist-info/LICENSE
urpameasure-0.1.1.dist-info/METADATA
urpameasure-0.1.1.dist-info/WHEEL
urpameasure-0.1.1.dist-info/top_level.txt
urpameasure-0.1.1.dist-info/RECORD
