Metadata-Version: 2.1
Name: urpameasure
Version: 0.1.1
Summary: Module containing wrapper classes for sending measurements with Management Console and Sydesk used with UltimateRPA robots
Home-page: https://github.com/ultimaterpa/urpameasure
Author: anerold
Author-email: support@ultimaterpa.cz
License: MIT
Keywords: Robotic Process Automation,RPA,UltimateRPA,measurement
Platform: UNKNOWN
Classifier: Intended Audience :: Developers
Classifier: Programming Language :: Python :: 3.7
Classifier: Operating System :: Microsoft :: Windows
Classifier: License :: OSI Approved :: MIT License
Requires-Python: >=3.7
